twmux/__init__.py
twmux/bin/__init__.py
twmux/bin/cli.py
twmux/lib/__init__.py
twmux/lib/execution.py
twmux/lib/safe_input.py
twmux-0.1.0.dist-info/METADATA
twmux-0.1.0.dist-info/WHEEL
twmux-0.1.0.dist-info/entry_points.txt
twmux-0.1.0.dist-info/top_level.txt
twmux-0.1.0.dist-info/RECORD
