Metadata-Version: 2.4
Name: twmux
Version: 0.1.0
Summary: Race-condition-safe tmux wrapper for coding agents
Author-email: sysid <sysid@gmx.de>
Requires-Python: >=3.13
Requires-Dist: libtmux>=0.46
Requires-Dist: typer>=0.15
Requires-Dist: rich>=13.0
Provides-Extra: dev
Requires-Dist: build>=1.0; extra == "dev"
Requires-Dist: pytest>=8.0; extra == "dev"
Requires-Dist: pytest-cov>=6.0; extra == "dev"
Requires-Dist: ruff>=0.9; extra == "dev"
Requires-Dist: twine>=6.0; extra == "dev"
